Quickdir/Quickdir.py
Quickdir/__init__.py
Quickdir/config.py
Quickdir-0.0.1.dist-info/LICENSE
Quickdir-0.0.1.dist-info/METADATA
Quickdir-0.0.1.dist-info/WHEEL
Quickdir-0.0.1.dist-info/top_level.txt
Quickdir-0.0.1.dist-info/RECORD
