Metadata-Version: 2.1
Name: Quickdir
Version: 0.0.1
Summary: A package to create complex directories in single step using JSON objects.
Home-page: https://github.com/Viwarrior/Quickdir
Author: Avinash
Author-email: avinashwc2011@gmail.com
License: UNKNOWN
Platform: UNKNOWN
Classifier: Programming Language :: Python :: 3
Classifier: License :: OSI Approved :: MIT License
Classifier: Operating System :: OS Independent
Requires-Python: >=3.5
